log2csv/__init__.py
log2csv/patterns/aws
log2csv/patterns/bacula
log2csv/patterns/bro
log2csv/patterns/exim
log2csv/patterns/firewalls
log2csv/patterns/grok
log2csv/patterns/grok-patterns
log2csv/patterns/haproxy
log2csv/patterns/java
log2csv/patterns/junos
log2csv/patterns/linux-syslog
log2csv/patterns/mcollective
log2csv/patterns/mcollective-patterns
log2csv/patterns/mongodb
log2csv/patterns/nagios
log2csv/patterns/postgresql
log2csv/patterns/rails
log2csv/patterns/redis
log2csv/patterns/ruby
log2csv-1.0.0.dist-info/METADATA
log2csv-1.0.0.dist-info/RECORD
log2csv-1.0.0.dist-info/WHEEL
log2csv-1.0.0.dist-info/entry_points.txt
log2csv-1.0.0.dist-info/top_level.txt
test/__init__.py
test/test_log2csv.py
test/patterns/test
