Metadata-Version: 2.1
Name: log2csv
Version: 1.0.0
Summary: A tool to parse log files into csv, using a grok-like pattern
Home-page: https://github.com/quick-sort/log2csv
Author: Rui Zhou
Author-email: quicksort@outlook.com
License: UNKNOWN
Platform: UNKNOWN
Classifier: Programming Language :: Python :: 3
Classifier: License :: OSI Approved :: MIT License
Classifier: Operating System :: OS Independent
Requires-Dist: regex
